gitflow_pyproject_version_bumper/__init__.py
gitflow_pyproject_version_bumper/__main__.py
gitflow_pyproject_version_bumper/post_checkout.py
gitflow_pyproject_version_bumper-0.1.4.dist-info/LICENSE
gitflow_pyproject_version_bumper-0.1.4.dist-info/METADATA
gitflow_pyproject_version_bumper-0.1.4.dist-info/WHEEL
gitflow_pyproject_version_bumper-0.1.4.dist-info/RECORD
