Metadata-Version: 2.1
Name: gitflow-pyproject-version-bumper
Version: 0.1.4
Summary: Automatic pyproject.toml based app version bumper
Home-page: https://github.com/booqoffsky/gitflow-pyproject-version-bumper
License: MIT
Keywords: gitflow,version,bumper,auto,pyproject,poetry,updater
Author: Grigory Bukovsky
Author-email: booqoffsky@yandex.ru
Requires-Python: >=3.8,<4.0
Classifier: License :: OSI Approved :: MIT License
Classifier: Programming Language :: Python :: 3
Classifier: Programming Language :: Python :: 3.8
Classifier: Programming Language :: Python :: 3.9
Classifier: Programming Language :: Python :: 3.10
Classifier: Programming Language :: Python :: 3.11
Requires-Dist: GitPython (>=3.1.31,<4.0.0)
Requires-Dist: tomlkit (>=0.11.7,<0.12.0)
Project-URL: Repository, https://github.com/booqoffsky/gitflow-pyproject-version-bumper
